spin_dependent_d_band_center/__init__.py
spin_dependent_d_band_center/main.py
spin_dependent_d_band_center-1.0.5.dist-info/METADATA
spin_dependent_d_band_center-1.0.5.dist-info/WHEEL
spin_dependent_d_band_center-1.0.5.dist-info/entry_points.txt
spin_dependent_d_band_center-1.0.5.dist-info/top_level.txt
spin_dependent_d_band_center-1.0.5.dist-info/RECORD
