Metadata-Version: 2.4
Name: Spin-dependent-d-band-center
Version: 1.0.5
Summary: Package for spin-dependent d-band center app
Author: Satadeep
License: MIT
Requires-Python: >=3.9
